mindsdb_evaluator/__init__.py
mindsdb_evaluator/accuracy/__init__.py
mindsdb_evaluator/accuracy/classification.py
mindsdb_evaluator/accuracy/forecasting.py
mindsdb_evaluator/accuracy/general.py
mindsdb_evaluator/accuracy/llm_generation.py
mindsdb_evaluator/accuracy/regression.py
mindsdb_evaluator/calibration/__init__.py
mindsdb_evaluator/calibration/ece.py
mindsdb_evaluator/helpers/general.py
mindsdb_evaluator-0.0.20.dist-info/LICENSE
mindsdb_evaluator-0.0.20.dist-info/METADATA
mindsdb_evaluator-0.0.20.dist-info/WHEEL
mindsdb_evaluator-0.0.20.dist-info/RECORD
