Metadata-Version: 2.3
Name: mindsdb-evaluator
Version: 0.0.20
Summary: Model evaluation for Machine Learning pipelines.
License: GPL-3.0
Author: MindsDB Inc.
Author-email: hello@mindsdb.com
Requires-Python: >=3.10,<3.14
Classifier: License :: OSI Approved :: GNU General Public License v3 (GPLv3)
Classifier: Programming Language :: Python :: 3
Classifier: Programming Language :: Python :: 3.10
Classifier: Programming Language :: Python :: 3.11
Classifier: Programming Language :: Python :: 3.12
Classifier: Programming Language :: Python :: 3.13
Provides-Extra: rag
Requires-Dist: dataprep-ml (==0.0.25)
Requires-Dist: datasets (>=2.20.0,<3.0.0) ; extra == "rag"
Requires-Dist: h11 (>=0.16.0) ; extra == "rag"
Requires-Dist: numpy (>=1,<2)
Requires-Dist: pandas (>=2,<3)
Requires-Dist: ragas (>=0.1.13,<0.2.0) ; extra == "rag"
Requires-Dist: scikit-learn (==1.5.2)
Requires-Dist: type-infer (==0.0.25)
